<manifest alg="2" build="2018.1.0.386" opt="true" iceEnabled="true" iceMarkupVersion="2" iceEnabledOptions="link,responsive,cachebuster,textStyling" exportTarget="other" domain="http://AnneBush.github.io" resolutions="1x,2x" timestamp="1528730187531">
  <folder name="css">
    <file name="site_global.css" crc="444006867"/>
    <file name="index.css" crc="400537727" ref="index"/>
    <file name="nomq_index.css" crc="98164442" ref="index"/>
    <file name="book-2-sale.css" crc="142787257" ref="book-2-sale"/>
    <file name="nomq_book-2-sale.css" crc="3893903653" ref="book-2-sale"/>
    <file name="book-1-sale.css" crc="4047825682" ref="book-1-sale"/>
    <file name="nomq_book-1-sale.css" crc="3949514201" ref="book-1-sale"/>
    <file name="book-1-thank.css" crc="326529595" ref="book-1-thank"/>
    <file name="nomq_book-1-thank.css" crc="3813283272" ref="book-1-thank"/>
    <file name="book-2-thank.css" crc="282551400" ref="book-2-thank"/>
    <file name="nomq_book-2-thank.css" crc="3775770793" ref="book-2-thank"/>
  </folder>
  <folder name="scripts">
    <file name="jquery-1.8.3.min.js" crc="209076791" ref="index:book-1-sale:book-2-sale:book-1-thank:book-2-thank"/>
    <file name="museutils.js" crc="340535759" ref="index:book-1-sale:book-2-sale:book-1-thank:book-2-thank"/>
    <file name="whatinput.js" crc="86476730" ref="index:book-1-sale:book-2-sale:book-1-thank:book-2-thank"/>
    <file name="museconfig.js" crc="310584261" ref="index:book-1-sale:book-2-sale:book-1-thank:book-2-thank"/>
    <file name="jquery.musemenu.js" crc="510910590" ref="index:book-1-sale:book-2-sale:book-1-thank:book-2-thank"/>
    <file name="jquery.watch.js" crc="51536988" ref="index:book-1-sale:book-2-sale:book-1-thank:book-2-thank"/>
    <file name="html5shiv.js" crc="4241844378" ref="index:book-1-sale:book-2-sale:book-1-thank:book-2-thank"/>
    <file name="jquery.museresponsive.js" crc="527716135" ref="index:book-1-sale:book-2-sale:book-1-thank:book-2-thank"/>
    <file name="require.js" crc="7928878" ref="index:book-1-sale:book-2-sale:book-1-thank:book-2-thank"/>
  </folder>
  <folder name="images">
    <file name="master-favicon.ico" crc="3903758046" ref="index"/>
    <file name="header-01.png" crc="3923944206" seo="true" ref="index:book-1-sale:book-2-sale:book-1-thank:book-2-thank">
      <caption webpage="index" alt=""/>
      <caption webpage="index" alt=""/>
      <caption webpage="index" alt=""/>
      <caption webpage="index" alt=""/>
      <caption webpage="index" alt=""/>
      <caption webpage="index" alt=""/>
      <caption webpage="index" alt=""/>
      <caption webpage="book-2-thank" alt=""/>
      <caption webpage="book-2-thank" alt=""/>
      <caption webpage="book-2-thank" alt=""/>
      <caption webpage="book-2-thank" alt=""/>
      <caption webpage="book-2-thank" alt=""/>
      <caption webpage="book-2-thank" alt=""/>
      <caption webpage="book-2-thank" alt=""/>
      <caption webpage="book-1-thank" alt=""/>
      <caption webpage="book-1-thank" alt=""/>
      <caption webpage="book-1-thank" alt=""/>
      <caption webpage="book-1-thank" alt=""/>
      <caption webpage="book-1-thank" alt=""/>
      <caption webpage="book-1-thank" alt=""/>
      <caption webpage="book-1-thank" alt=""/>
      <caption webpage="book-1-sale" alt=""/>
      <caption webpage="book-1-sale" alt=""/>
      <caption webpage="book-1-sale" alt=""/>
      <caption webpage="book-1-sale" alt=""/>
      <caption webpage="book-1-sale" alt=""/>
      <caption webpage="book-1-sale" alt=""/>
      <caption webpage="book-1-sale" alt=""/>
      <caption webpage="book-2-sale" alt=""/>
      <caption webpage="book-2-sale" alt=""/>
      <caption webpage="book-2-sale" alt=""/>
      <caption webpage="book-2-sale" alt=""/>
      <caption webpage="book-2-sale" alt=""/>
      <caption webpage="book-2-sale" alt=""/>
      <caption webpage="book-2-sale" alt=""/>
    </file>
    <file name="01.png" crc="3888863177" seo="true" ref="index">
      <caption webpage="index" alt=""/>
    </file>
    <file name="02.png" crc="3975367874" seo="true" ref="index">
      <caption webpage="index" alt=""/>
    </file>
    <file name="03.png" crc="3849713596" seo="true" ref="index">
      <caption webpage="index" alt=""/>
    </file>
    <file name="book-1200x350.jpg" crc="3905785162" seo="true" ref="index">
      <caption webpage="index" alt=""/>
      <caption webpage="index" alt=""/>
    </file>
    <file name="book-2200x350.jpg" crc="78791029" seo="true" ref="index">
      <caption webpage="index" alt=""/>
    </file>
    <file name="0176x103.png" crc="231679507" seo="true" ref="index">
      <caption webpage="index" alt=""/>
    </file>
    <file name="0276x108.png" crc="4282910378" seo="true" ref="index">
      <caption webpage="index" alt=""/>
    </file>
    <file name="0376x103.png" crc="4053135690" seo="true" ref="index">
      <caption webpage="index" alt=""/>
    </file>
    <file name="book-2.jpg" crc="78791029" seo="true" ref="index:book-2-sale:book-1-thank:book-2-thank">
      <caption webpage="index" alt=""/>
      <caption webpage="book-2-thank" alt=""/>
      <caption webpage="book-1-thank" alt=""/>
      <caption webpage="book-2-sale" alt=""/>
    </file>
    <file name="0167x90.png" crc="4006243694" seo="true" ref="index">
      <caption webpage="index" alt=""/>
    </file>
    <file name="0267x95.png" crc="4087473386" seo="true" ref="index">
      <caption webpage="index" alt=""/>
    </file>
    <file name="0367x90.png" crc="384272256" seo="true" ref="index">
      <caption webpage="index" alt=""/>
    </file>
    <file name="book-1134x234.jpg" crc="312130826" seo="true" ref="index">
      <caption webpage="index" alt=""/>
      <caption webpage="index" alt=""/>
      <caption webpage="index" alt=""/>
      <caption webpage="index" alt=""/>
      <caption webpage="index" alt=""/>
    </file>
    <file name="book-2134x235.jpg" crc="3891578573" seo="true" ref="index">
      <caption webpage="index" alt=""/>
      <caption webpage="index" alt=""/>
      <caption webpage="index" alt=""/>
      <caption webpage="index" alt=""/>
    </file>
    <file name="0157x77.png" crc="4206744483" seo="true" ref="index">
      <caption webpage="index" alt=""/>
    </file>
    <file name="0257x81.png" crc="3878402233" seo="true" ref="index">
      <caption webpage="index" alt=""/>
    </file>
    <file name="0357x77.png" crc="3894614694" seo="true" ref="index">
      <caption webpage="index" alt=""/>
    </file>
    <file name="0145x60.png" crc="4159795125" seo="true" ref="index">
      <caption webpage="index" alt=""/>
    </file>
    <file name="0245x64.png" crc="167338109" seo="true" ref="index">
      <caption webpage="index" alt=""/>
    </file>
    <file name="0345x60.png" crc="377328115" seo="true" ref="index">
      <caption webpage="index" alt=""/>
    </file>
    <file name="0136x48.png" crc="3920805722" seo="true" ref="index">
      <caption webpage="index" alt=""/>
    </file>
    <file name="0236x51.png" crc="470634822" seo="true" ref="index">
      <caption webpage="index" alt=""/>
    </file>
    <file name="0336x48.png" crc="3766033890" seo="true" ref="index">
      <caption webpage="index" alt=""/>
    </file>
    <file name="0140x54.png" crc="162651484" seo="true" ref="index">
      <caption webpage="index" alt=""/>
    </file>
    <file name="0240x57.png" crc="3906105818" seo="true" ref="index">
      <caption webpage="index" alt=""/>
    </file>
    <file name="0340x54.png" crc="4092043632" seo="true" ref="index">
      <caption webpage="index" alt=""/>
    </file>
    <file name="book-2136x237.jpg" crc="3906512621" seo="true" ref="index">
      <caption webpage="index" alt=""/>
    </file>
    <file name="blank.gif" crc="4208392903" ref="index:book-1-sale:book-2-sale:book-1-thank:book-2-thank"/>
    <file name="book-1.jpg" crc="3905785162" seo="true" ref="book-1-sale:book-1-thank:book-2-thank">
      <caption webpage="book-2-thank" alt=""/>
      <caption webpage="book-1-thank" alt=""/>
      <caption webpage="book-1-sale" alt=""/>
    </file>
    <file name="book-2134x234.jpg" crc="3891578573" seo="true" ref="book-2-sale">
      <caption webpage="book-2-sale" alt=""/>
      <caption webpage="book-2-sale" alt=""/>
      <caption webpage="book-2-sale" alt=""/>
      <caption webpage="book-2-sale" alt=""/>
    </file>
  </folder>
  <file name="index.html" crc="4015994251" seo="true" mt="1528729993463" redirect="true"/>
  <file name="book-1-sale.html" crc="3915995556" seo="true" mt="1528730023752" redirect="true"/>
  <file name="book-2-sale.html" crc="328681094" seo="true" mt="1528730047676" redirect="true"/>
  <file name="book-1-thank.html" crc="4080476085" seo="true" mt="1528730081012" redirect="true"/>
  <file name="book-2-thank.html" crc="4109876845" seo="true" mt="1528730094752" redirect="true"/>
</manifest>